piehydra/__init__.py
piehydra/install.py
piehydra-0.0.1.dist-info/METADATA
piehydra-0.0.1.dist-info/WHEEL
piehydra-0.0.1.dist-info/top_level.txt
piehydra-0.0.1.dist-info/RECORD
