Metadata-Version: 2.1
Name: piehydra
Version: 0.0.1
Summary: wrapper for hydra-thc (bruteforcing tool)
Home-page: UNKNOWN
Author: plusleft
License: UNKNOWN
Platform: UNKNOWN
